amlc/__init__.py
amlc/covariance_matrix.py
amlc/marginalized_likelihood.py
amlc-1.1.dist-info/LICENSE
amlc-1.1.dist-info/METADATA
amlc-1.1.dist-info/WHEEL
amlc-1.1.dist-info/top_level.txt
amlc-1.1.dist-info/RECORD
