Metadata-Version: 2.1
Name: amlc
Version: 1.1
Summary: Analytic marginalization over linear continuum parameters
Home-page: https://github.com/ktchrn/amlc
Author: Kirill Tchernyshyov
Author-email: ktcherny@gmail.com
License: MIT
Platform: UNKNOWN
Requires-Python: >3.5
Requires-Dist: numpy
Requires-Dist: scipy
